__init__.py
converter/__init__.py
converter/_version.py
converter/converter.py
converter/indent.py
converter/motionarea.py
converter/pipemessage.py
converter/success.txt
converter/old_motorhome/__init__.py
converter/old_motorhome/motorhome.py
converter/shim/__init__.py
converter/shim/controllertype.py
converter/shim/functions.py
converter/shim/globals.py
converter/shim/group.py
converter/shim/motor.py
converter/shim/motorhome.py
converter/shim/plc.py
pmac_motorhome/__init__.py
pmac_motorhome/__main__.py
pmac_motorhome/_version.py
pmac_motorhome/commands.py
pmac_motorhome/constants.py
pmac_motorhome/group.py
pmac_motorhome/motor.py
pmac_motorhome/onlyaxes.py
pmac_motorhome/plc.py
pmac_motorhome/plcgenerator.py
pmac_motorhome/sequences.py
pmac_motorhome/snippets.py
pmac_motorhome/template.py
pmac_motorhome/snippets/power/check_homed.pmc.jinja
pmac_motorhome/snippets/power/continue_home_maintain_axes_offset.pmc.jinja
pmac_motorhome/snippets/power/debug_pause.pmc.jinja
pmac_motorhome/snippets/power/disable_axis_limits.pmc.jinja
pmac_motorhome/snippets/power/disable_limits.pmc.jinja
pmac_motorhome/snippets/power/drive_off_home.pmc.jinja
pmac_motorhome/snippets/power/drive_relative.pmc.jinja
pmac_motorhome/snippets/power/drive_to_hard_limit.pmc.jinja
pmac_motorhome/snippets/power/drive_to_home.pmc.jinja
pmac_motorhome/snippets/power/drive_to_home_if_on_limit.pmc.jinja
pmac_motorhome/snippets/power/drive_to_hstop.pmc.jinja
pmac_motorhome/snippets/power/drive_to_initial_pos.pmc.jinja
pmac_motorhome/snippets/power/drive_to_limit.pmc.jinja
pmac_motorhome/snippets/power/drive_to_soft_limit.pmc.jinja
pmac_motorhome/snippets/power/home.pmc.jinja
pmac_motorhome/snippets/power/jog_if_on_limit.pmc.jinja
pmac_motorhome/snippets/power/plc.pmc.jinja
pmac_motorhome/snippets/power/post_home_action.pmc.jinja
pmac_motorhome/snippets/power/pre_home_action.pmc.jinja
pmac_motorhome/snippets/power/restore_limits.pmc.jinja
pmac_motorhome/snippets/power/store_position_diff.pmc.jinja
pmac_motorhome-1.12.dist-info/licenses/LICENSE
pmac_motorhome-1.12.dist-info/METADATA
pmac_motorhome-1.12.dist-info/WHEEL
pmac_motorhome-1.12.dist-info/entry_points.txt
pmac_motorhome-1.12.dist-info/top_level.txt
pmac_motorhome-1.12.dist-info/RECORD
